ocf_github_workflow_test/__init__.py
ocf_github_workflow_test-0.1.47.dist-info/LICENSE
ocf_github_workflow_test-0.1.47.dist-info/METADATA
ocf_github_workflow_test-0.1.47.dist-info/WHEEL
ocf_github_workflow_test-0.1.47.dist-info/top_level.txt
ocf_github_workflow_test-0.1.47.dist-info/RECORD
