Metadata-Version: 2.1
Name: ocf-github-workflow-test
Version: 0.1.47
Summary: Test package for our github workflows
Author: Open Climate Fix
Project-URL: Homepage, https://github.com/openclimatefix/.github-test
Classifier: Programming Language :: Python :: 3
Classifier: License :: OSI Approved :: MIT License
Classifier: Operating System :: OS Independent
Requires-Python: >=3.10
License-File: LICENSE
Requires-Dist: pytest (==7.2.2)
Requires-Dist: pytest-cov (==4.0.0)
